odoo8_addon_medical_his-8.0.1.1.0.99.dev4-py2.7-nspkg.pth
odoo8_addon_medical_his-8.0.1.1.0.99.dev4.dist-info/DESCRIPTION.rst
odoo8_addon_medical_his-8.0.1.1.0.99.dev4.dist-info/METADATA
odoo8_addon_medical_his-8.0.1.1.0.99.dev4.dist-info/RECORD
odoo8_addon_medical_his-8.0.1.1.0.99.dev4.dist-info/WHEEL
odoo8_addon_medical_his-8.0.1.1.0.99.dev4.dist-info/metadata.json
odoo8_addon_medical_his-8.0.1.1.0.99.dev4.dist-info/namespace_packages.txt
odoo8_addon_medical_his-8.0.1.1.0.99.dev4.dist-info/top_level.txt
odoo_addons/medical_his/README.rst
odoo_addons/medical_his/__init__.py
odoo_addons/medical_his/__openerp__.py
odoo_addons/medical_his/i18n/pt_BR.po
odoo_addons/medical_his/i18n/sl.po
odoo_addons/medical_his/models/__init__.py
odoo_addons/medical_his/models/abstract_medical_hospital.py
odoo_addons/medical_his/models/medical_hospital_bed.py
odoo_addons/medical_his/models/medical_hospital_or.py
odoo_addons/medical_his/models/medical_hospital_room.py
odoo_addons/medical_his/models/medical_hospital_unit.py
odoo_addons/medical_his/models/medical_hospital_zone.py
odoo_addons/medical_his/security/ir.model.access.csv
odoo_addons/medical_his/tests/__init__.py
odoo_addons/medical_his/tests/test_medical_hospital_bed.py
odoo_addons/medical_his/tests/test_medical_hospital_or.py
odoo_addons/medical_his/tests/test_medical_hospital_room.py
odoo_addons/medical_his/tests/test_medical_hospital_unit.py
odoo_addons/medical_his/tests/test_medical_hospital_zone.py
odoo_addons/medical_his/tests/data/medical_his_data.xml
odoo_addons/medical_his/views/medical_hospital_bed_view.xml
odoo_addons/medical_his/views/medical_hospital_menu.xml
odoo_addons/medical_his/views/medical_hospital_or_view.xml
odoo_addons/medical_his/views/medical_hospital_room_view.xml
odoo_addons/medical_his/views/medical_hospital_unit_view.xml
odoo_addons/medical_his/views/medical_hospital_zone_view.xml
