Metadata-Version: 2.0
Name: odoo8-addon-medical-his
Version: 8.0.1.1.0.99.dev4
Summary: Medical Hospital
Home-page: https://github.com/OCA/vertical-medical/
Author: Odoo Medical Team, Odoo Community Association (OCA)
Author-email: support@odoo-community.org
License: AGPL-3
Platform: UNKNOWN
Classifier: Programming Language :: Python :: 2.7
Classifier: Framework :: Odoo
Classifier: License :: OSI Approved :: GNU Affero General Public License v3
Requires-Dist: odoo (<9.0a,>=8.0a)
Requires-Dist: odoo8-addon-medical
